EnabledFF/hdl/sv/EnabledFF.sv
module EnabledFF #(parameter size=32) (
  input   logic            clk,
  input   logic            reset,
  input   logic            en,
  input   logic [size-1:0] d,
  output  logic [size-1:0] q
);

  // asynchronous reset
  always_ff @(posedge clk, posedge reset)
    if (reset) q <= 1'b0;
    else if (en) q <= d;

`ifdef  COCOTB_SIM 
initial
 begin
    $dumpfile("wave_sv.vcd");
    $dumpvars(
      0,
      clk,
      reset,
      en,
      d,
      q
    );
    #5;
 end
 `endif

endmodule

EnabledFF/tests/wave_sv.vcd
$date
	Fri Nov 11 12:40:51 2022
$end
$version
	Icarus Verilog
$end
$timescale
	1ps
$end
$scope module EnabledFF $end
$var wire 1 ! clk $end
$upscope $end
$scope module EnabledFF $end
$var wire 1 " reset $end
$upscope $end
$scope module EnabledFF $end
$var wire 1 # en $end
$upscope $end
$scope module EnabledFF $end
$var wire 32 $ d [31:0] $end
$upscope $end
$scope module EnabledFF $end
$var reg 32 % q [31:0] $end
$upscope $end
$enddefinitions $end
#0
$dumpvars
bx %
bz $
z#
z"
1!
$end
#5000000
b0 %
1"
0!
#10000000
1!
#15000000
0#
0"
b0 $
0!
#20000000
1!
#25000000
1#
0!
#30000000
1!
#35000000
0#
1"
0!
#40000000
1!
#45000000
1#
0!
#50000000
1!
#55000000
0#
0"
b1 $
0!
#60000000
1!
#65000000
1#
0!
#70000000
b1 %
1!
#75000000
b0 %
0#
1"
0!
#80000000
1!
#85000000
1#
0!
#90000000
1!
#95000000
0#
0"
b10 $
0!
#100000000
1!
#105000000
1#
0!
#110000000
b10 %
1!
#115000000
b0 %
0#
1"
0!
#120000000
1!
#125000000
1#
0!
#130000000
1!
#135000000
0#
0"
b11 $
0!
#140000000
1!
#145000000
1#
0!
#150000000
b11 %
1!
#155000000
b0 %
0#
1"
0!
#160000000
1!
#165000000
1#
0!
#170000000
1!
#175000000
0#
0"
b100 $
0!
#180000000
1!
#185000000
1#
0!
#190000000
b100 %
1!
#195000000
b0 %
0#
1"
0!
#200000000
1!
#205000000
1#
0!
#210000000
1!
#215000000
0#
0"
b101 $
0!
#220000000
1!
#225000000
1#
0!
#230000000
b101 %
1!
#235000000
b0 %
0#
1"
0!
#240000000
1!
#245000000
1#
0!
#250000000
1!
#255000000
0#
0"
b110 $
0!
#260000000
1!
#265000000
1#
0!
#270000000
b110 %
1!
#275000000
b0 %
0#
1"
0!
#280000000
1!
#285000000
1#
0!
#290000000
1!
#295000000
0#
0"
b111 $
0!
#300000000
1!
#305000000
1#
0!
#310000000
b111 %
1!
#315000000
b0 %
0#
1"
0!
#320000000
1!
#325000000
1#
0!
#330000000
1!
#335000000
0#
0"
b1000 $
0!
#340000000
1!
#345000000
1#
0!
#350000000
b1000 %
1!
#355000000
b0 %
0#
1"
0!
#360000000
1!
#365000000
1#
0!
#370000000
1!
#375000000
0#
0"
b1001 $
0!
#380000000
1!
#385000000
1#
0!
#390000000
b1001 %
1!
#395000000
b0 %
0#
1"
0!
#400000000
1!
#405000000
1#
0!
#410000000
1!
#415000000
0#
0"
b1010 $
0!
#420000000
1!
#425000000
1#
0!
#430000000
b1010 %
1!
#435000000
b0 %
0#
1"
0!
#440000000
1!
#445000000
1#
0!
#450000000
1!
#455000000
0#
0"
b1011 $
0!
#460000000
1!
#465000000
1#
0!
#470000000
b1011 %
1!
#475000000
b0 %
0#
1"
0!
#480000000
1!
#485000000
1#
0!
#490000000
1!
#495000000
0#
0"
b1100 $
0!
#500000000
1!
#505000000
1#
0!
#510000000
b1100 %
1!
#515000000
b0 %
0#
1"
0!
#520000000
1!
#525000000
1#
0!
#530000000
1!
#535000000
0#
0"
b1101 $
0!
#540000000
1!
#545000000
1#
0!
#550000000
b1101 %
1!
#555000000
b0 %
0#
1"
0!
#560000000
1!
#565000000
1#
0!
#570000000
1!
#575000000
0#
0"
b1110 $
0!
#580000000
1!
#585000000
1#
0!
#590000000
b1110 %
1!
#595000000
b0 %
0#
1"
0!
#600000000
1!
#605000000
1#
0!
#610000000
1!
#615000000
0#
0"
b1111 $
0!
#620000000
1!
#625000000
1#
0!
#630000000
b1111 %
1!
#635000000
b0 %
0#
1"
0!
#640000000
1!
#645000000
1#
0!
